restackio/integrations/openai/__init__.py
restackio/integrations/openai/functions/__init__.py
restackio/integrations/openai/functions/chat/__init__.py
restackio/integrations/openai/functions/chat/completions_base.py
restackio/integrations/openai/functions/chat/completions_stream.py
restackio/integrations/openai/py.typed
restackio/integrations/openai/service.py
restackio/integrations/openai/task_queue.py
restackio/integrations/openai/utils/__init__.py
restackio/integrations/openai/utils/client.py
restackio/integrations/openai/utils/cost.py
restackio_integrations_openai-0.0.1.dist-info/METADATA
restackio_integrations_openai-0.0.1.dist-info/WHEEL
restackio_integrations_openai-0.0.1.dist-info/RECORD
