Metadata-Version: 2.1
Name: restackio.integrations.openai
Version: 0.0.1
Summary: OpenAI integration for Restack AI
Author: Restack Team
Author-email: service@restack.io
Requires-Python: >=3.8,<4.0
Classifier: Programming Language :: Python :: 3
Classifier: Programming Language :: Python :: 3.8
Classifier: Programming Language :: Python :: 3.9
Classifier: Programming Language :: Python :: 3.10
Classifier: Programming Language :: Python :: 3.11
Classifier: Programming Language :: Python :: 3.12
Requires-Dist: openai (>=1.52.0,<2.0.0)
Requires-Dist: pydantic (>=2.9.2,<3.0.0)
Requires-Dist: restackio-ai (>=0.0.11,<0.0.12)
